octk/__init__.py
octk/emailer.py
octk/projectify.py
octk/pytree.py
octk/assets/Node.gitignore
octk/assets/Python.gitignore
octk-0.1.0.dist-info/METADATA
octk-0.1.0.dist-info/WHEEL
octk-0.1.0.dist-info/top_level.txt
octk-0.1.0.dist-info/RECORD
