Metadata-Version: 2.1
Name: octk
Version: 0.1.0
Summary: Oakley's Common Toolkit
Author: oakla
Keywords: oakley,common,toolkit,octk,miscellaneous,directory structure
Requires-Dist: importlib-resources ; python_version < "3.10"
